shitty_google_wrapper/__init__.py
shitty_google_wrapper/client.py
shitty_google_wrapper-0.0.16.dist-info/METADATA
shitty_google_wrapper-0.0.16.dist-info/WHEEL
shitty_google_wrapper-0.0.16.dist-info/RECORD
